MANIFEST.in
setup.py
./__init__.py
./__openerp__.py
./edi_service.py
./controllers/__init__.py
./controllers/main.py
./models/__init__.py
./models/edi.py
./models/res_company.py
./models/res_currency.py
./models/res_partner.py
i18n/ar.po
i18n/cs.po
i18n/de.po
i18n/edi.pot
i18n/en_GB.po
i18n/es.po
i18n/es_CR.po
i18n/fi.po
i18n/fr.po
i18n/he.po
i18n/hr.po
i18n/hu.po
i18n/is.po
i18n/it.po
i18n/ja.po
i18n/lt.po
i18n/mk.po
i18n/ml.po
i18n/mn.po
i18n/nb.po
i18n/nl.po
i18n/nl_BE.po
i18n/pl.po
i18n/pt.po
i18n/pt_BR.po
i18n/ro.po
i18n/ru.po
i18n/sl.po
i18n/sv.po
i18n/tr.po
i18n/zh_CN.po
i18n/zh_TW.po
openerp_edi.egg-info/PKG-INFO
openerp_edi.egg-info/SOURCES.txt
openerp_edi.egg-info/dependency_links.txt
openerp_edi.egg-info/requires.txt
openerp_edi.egg-info/top_level.txt
static/src/img/knowledge.png
static/src/js/edi.js
test/edi_partner_test.yml